mcuuidButWorks/__init__.py
mcuuidButWorks/api.py
mcuuidButWorks/tools.py
mcuuidButWorks-0.3.dist-info/METADATA
mcuuidButWorks-0.3.dist-info/WHEEL
mcuuidButWorks-0.3.dist-info/top_level.txt
mcuuidButWorks-0.3.dist-info/RECORD
