Metadata-Version: 2.1
Name: mcuuidButWorks
Version: 0.3
Summary: Getting Minecraft Player Information from Mojang API.
Home-page: https://github.com/clerie/mcuuid
Author: Clemens Riese
Author-email: hallo@clerie.de
License: UNKNOWN
Platform: UNKNOWN
Classifier: Programming Language :: Python :: 3
Classifier: Programming Language :: Python :: 2
Classifier: License :: OSI Approved :: MIT License
Classifier: Operating System :: OS Independent
